{
  "restartable": "rs",
  "ignore": [".git", "node_modules/**/node_modules"],
  "verbose": true,
  "watch": [
    "./views/pug/*",
    "./server.js",
    "./auth.js",
    "./routes.js",
    "./public/*"
  ],
  "env": {
    "GITHUB_CLIENT_ID": "069410367fb04e4af852",
    "GITHUB_CLIENT_SECRET": "d8a1465455c1df47ab9995305807198f663fc483",
    "PORT": 3000,
    "NODE_ENV": "development",
    "SESSION_SECRET": "abc",
    "MONGO_URI": "mongodb+srv://fcc-olive4:gI2WKqT6WLC5lGUv@cluster0.khhwa.mongodb.net/fcc-advancednode?retryWrites=true&w=majority"
  },
  "ext": "js,json,pug,css"
}
